new_words_detection/__init__.py
new_words_detection/main.py
new_words_detection/wordSegment.py
new_words_detection-1.0.4.dist-info/LICENSE
new_words_detection-1.0.4.dist-info/METADATA
new_words_detection-1.0.4.dist-info/WHEEL
new_words_detection-1.0.4.dist-info/top_level.txt
new_words_detection-1.0.4.dist-info/RECORD
