Metadata-Version: 2.1
Name: new-words-detection
Version: 1.0.4
Summary: Chinese Words Segmentation Utilities
Home-page: https://github.com/skykiseki/NewWordDectection
Author: Wei, Zhihui
Author-email: evelinesdd@qq.com
License: MIT
Keywords: NLP,Chinese word detection,Chinese word segementation
Platform: UNKNOWN
Classifier: Intended Audience :: Developers
Classifier: License :: OSI Approved :: MIT License
Classifier: Operating System :: OS Independent
Classifier: Natural Language :: Chinese (Simplified)
Classifier: Natural Language :: Chinese (Traditional)
Classifier: Programming Language :: Python
Classifier: Programming Language :: Python :: 3
Classifier: Programming Language :: Python :: 3.6
Classifier: Programming Language :: Python :: 3.7
Classifier: Topic :: Text Processing
Classifier: Topic :: Text Processing :: Indexing
Classifier: Topic :: Text Processing :: Linguistic
Requires-Python: >=3.6
License-File: LICENSE
Requires-Dist: pandas
Requires-Dist: numpy
